README.rst
bvatar.py
setup.py
bvatar.egg-info/PKG-INFO
bvatar.egg-info/SOURCES.txt
bvatar.egg-info/dependency_links.txt
bvatar.egg-info/entry_points.txt
bvatar.egg-info/requires.txt
bvatar.egg-info/top_level.txt