Metadata-Version: 1.1
Name: bvatar
Version: 1.0.a2
Summary: Random-art avatar generation
Home-page: https://github.com/smileychris/bvatar
Author: Chris Beaven
Author-email: smileychris@gmail.com
License: BSD
Platform: any
Classifier: Development Status :: 3 - Alpha
Classifier: License :: OSI Approved :: BSD License
Classifier: Operating System :: OS Independent
Classifier: Intended Audience :: Developers
Classifier: Programming Language :: Python
Classifier: Programming Language :: Python :: 2.7
Classifier: Programming Language :: Python :: 3.3
Classifier: Programming Language :: Python :: 3.4
Classifier: Topic :: Multimedia :: Graphics
Classifier: Topic :: Software Development :: Libraries :: Python Modules
